<?xml version="1.0" encoding="iso-8859-1"?>

<root version="3.0" >

  <properties>
    <name>2E - 1E Properties</name>
    <version>1.3</version>
    <loadorder>99</loadorder>
    <description>
      <text>1E Saves, Matrix and Ability properties.</text>
      <website></website>
      <author>Celestian</author>
    </description>
    <ruleset>
      <name>2E</name>
<!--       <maxrelease>28</maxrelease>
      <minrelease>25</minrelease> -->
    </ruleset>
  </properties>

  <announcement text="AD&amp;D 1E Properties v1.3, AD&amp;D 2E version.\r--by Celestian 2017-2021" font="emotefont" icon="rulesetlogo_DungeonClassic" />
  <base>    
    <!-- High-level scripts -->
    <script name="DataCommonADND1e" file="scripts/data_common_adnd1e.lua" />
  </base>
    
</root>
